examples/readme_image.py
oipd/__init__.py
oipd/estimator.py
oipd/market_inputs.py
oipd/core/__init__.py
oipd/core/parity.py
oipd/core/pdf.py
oipd/graphics/__init__.py
oipd/graphics/matplot.py
oipd/graphics/publication.py
oipd/io/__init__.py
oipd/io/csv_reader.py
oipd/io/dataframe_reader.py
oipd/io/reader.py
oipd/pricing/__init__.py
oipd/pricing/black76.py
oipd/pricing/black_scholes.py
oipd/pricing/utils.py
oipd/vendor/__init__.py
oipd/vendor/yfinance/__init__.py
oipd/vendor/yfinance/reader.py
oipd-1.0.2.dist-info/licenses/LICENSE
oipd-1.0.2.dist-info/METADATA
oipd-1.0.2.dist-info/WHEEL
oipd-1.0.2.dist-info/top_level.txt
oipd-1.0.2.dist-info/RECORD
