Metadata-Version: 2.4
Name: oipd
Version: 1.0.2
Summary: Generate probability distributions on the future price of publicly traded securities using options data
Author-email: Henry Tian <tyrneh@gmail.com>, Jannic Holzer <jannic.holzer@gmail.com>, Chun Hei Hung <chunhei1848@gmail.com>, Melanie Chen <melaniechen28@gmail.com>
License: Apache License 2.0
Project-URL: Homepage, https://github.com/tyrneh/options-implied-probability
Project-URL: Bug Tracker, https://github.com/tyrneh/options-implied-probability/issues
Classifier: Programming Language :: Python :: 3
Classifier: Programming Language :: Python :: 3.10
Classifier: Programming Language :: Python :: 3.11
Classifier: Programming Language :: Python :: 3.12
Classifier: Programming Language :: Python :: 3.13
Classifier: Operating System :: MacOS
Classifier: Operating System :: POSIX :: Linux
Classifier: Topic :: Office/Business :: Financial :: Investment
Classifier: Development Status :: 4 - Beta
Classifier: Intended Audience :: Financial and Insurance Industry
Classifier: Intended Audience :: Science/Research
Requires-Python: >=3.10
License-File: LICENSE
Requires-Dist: numpy>=1.26.0
Requires-Dist: pandas>=2.1.0
Requires-Dist: scipy>=1.11.0
Requires-Dist: matplotlib>=3.8.0
Requires-Dist: matplotlib-label-lines>=0.6.0
Requires-Dist: traitlets>=5.12.0
Requires-Dist: yfinance>=0.2.60
Provides-Extra: minimal
Requires-Dist: numpy>=1.26.0; extra == "minimal"
Requires-Dist: pandas>=2.1.0; extra == "minimal"
Requires-Dist: scipy>=1.11.0; extra == "minimal"
Requires-Dist: matplotlib>=3.8.0; extra == "minimal"
Requires-Dist: matplotlib-label-lines>=0.6.0; extra == "minimal"
Requires-Dist: traitlets>=5.12.0; extra == "minimal"
Provides-Extra: dev
Requires-Dist: black>=24.3.0; extra == "dev"
Requires-Dist: isort>=5.13.0; extra == "dev"
Requires-Dist: pytest>=8.0.0; extra == "dev"
Requires-Dist: mypy>=1.8.0; extra == "dev"
Requires-Dist: build>=1.0.0; extra == "dev"
Dynamic: license-file
